pytest_pytorch/__init__.py
pytest_pytorch/_version.py
pytest_pytorch/plugin.py
pytest_pytorch-0.2.1.dist-info/LICENSE
pytest_pytorch-0.2.1.dist-info/METADATA
pytest_pytorch-0.2.1.dist-info/WHEEL
pytest_pytorch-0.2.1.dist-info/entry_points.txt
pytest_pytorch-0.2.1.dist-info/top_level.txt
pytest_pytorch-0.2.1.dist-info/RECORD
