Metadata-Version: 2.1
Name: pytest-pytorch
Version: 0.2.1
Summary: pytest plugin for a better developer experience when working with the PyTorch test suite
Home-page: https://github.com/Quansight/pytest-pytorch
Author: Philip Meier
Author-email: pmeier@quansight.com
License: BSD-3-Clause
Project-URL: Source, https://github.com/Quansight/pytest-pytorch
Project-URL: Documentation, https://github.com/Quansight/pytest-pytorch
Project-URL: Tracker, https://github.com/Quansight/pytest-pytorch/issues
Keywords: pytest,plugin,pytorch,torch
Platform: any
Classifier: Development Status :: 4 - Beta
Classifier: Framework :: Pytest
Classifier: Intended Audience :: Developers
Classifier: License :: OSI Approved :: BSD License
Classifier: Operating System :: OS Independent
Classifier: Programming Language :: Python :: 3.6
Classifier: Programming Language :: Python :: 3.7
Classifier: Programming Language :: Python :: 3.8
Classifier: Programming Language :: Python :: 3.9
Classifier: Topic :: Software Development :: Testing
Requires-Python: >=3.6
License-File: LICENSE
Requires-Dist: pytest
